gen_workflow_mcp_server/__init__.py
gen_workflow_mcp_server/conditional.py
gen_workflow_mcp_server/constant.py
gen_workflow_mcp_server/model.py
gen_workflow_mcp_server/prompt.py
gen_workflow_mcp_server/server.py
gen_workflow_mcp_server/steps.py
gen_workflow_mcp_server/base/base.md
gen_workflow_mcp_server/file/reader.py
gen_workflow_mcp_server/file/writer.py
gen_workflow_mcp_server-0.0.3.dist-info/METADATA
gen_workflow_mcp_server-0.0.3.dist-info/WHEEL
gen_workflow_mcp_server-0.0.3.dist-info/entry_points.txt
gen_workflow_mcp_server-0.0.3.dist-info/RECORD
